{
  "CF100338707": {
    "contest_id": 1036,
    "language": "GNU C++17 (64)",
    "path": "codeforces/1036/C.cpp",
    "problem_index": "C",
    "problem_name": "Classy Numbers",
    "problem_url": "https://codeforces.com/contest/1036/problem/C",
    "submission_id": "CF100338707",
    "submission_url": "https://codeforces.com/contest/1036/submission/100338707",
    "tags": [
      "combinatorics",
      "dp",
      "*1900"
    ],
    "timestamp": "Dec/04/2020 14:04"
  },
  "CF97265796": {
    "contest_id": 1291,
    "language": "GNU C++17 (64)",
    "path": "codeforces/1291/B.cpp",
    "problem_index": "B",
    "problem_name": "Array Sharpening",
    "problem_url": "https://codeforces.com/contest/1291/problem/B",
    "submission_id": "CF97265796",
    "submission_url": "https://codeforces.com/contest/1291/submission/97265796",
    "tags": [
      "greedy",
      "implementation",
      "*1300"
    ],
    "timestamp": "Oct/31/2020 23:03"
  },
  "CF97290804": {
    "contest_id": 1354,
    "language": "GNU C++17 (64)",
    "path": "codeforces/1354/B.cpp",
    "problem_index": "B",
    "problem_name": "Ternary String",
    "problem_url": "https://codeforces.com/contest/1354/problem/B",
    "submission_id": "CF97290804",
    "submission_url": "https://codeforces.com/contest/1354/submission/97290804",
    "tags": [
      "binary search",
      "dp",
      "implementation",
      "two pointers",
      "*1200"
    ],
    "timestamp": "Nov/01/2020 11:57"
  },
  "CF97291354": {
    "contest_id": 1354,
    "language": "GNU C++17 (64)",
    "path": "codeforces/1354/B.cpp",
    "problem_index": "B",
    "problem_name": "Ternary String",
    "problem_url": "https://codeforces.com/contest/1354/problem/B",
    "submission_id": "CF97291354",
    "submission_url": "https://codeforces.com/contest/1354/submission/97291354",
    "tags": [
      "binary search",
      "dp",
      "implementation",
      "two pointers",
      "*1200"
    ],
    "timestamp": "Nov/01/2020 12:06"
  },
  "CF97291980": {
    "contest_id": 552,
    "language": "GNU C++17 (64)",
    "path": "codeforces/552/B.cpp",
    "problem_index": "B",
    "problem_name": "Vanya and Books",
    "problem_url": "https://codeforces.com/contest/552/problem/B",
    "submission_id": "CF97291980",
    "submission_url": "https://codeforces.com/contest/552/submission/97291980",
    "tags": [
      "implementation",
      "math",
      "*1200"
    ],
    "timestamp": "Nov/01/2020 12:15"
  },
  "CF97293044": {
    "contest_id": 454,
    "language": "GNU C++17 (64)",
    "path": "codeforces/454/B.cpp",
    "problem_index": "B",
    "problem_name": "Little Pony and Sort by Shift",
    "problem_url": "https://codeforces.com/contest/454/problem/B",
    "submission_id": "CF97293044",
    "submission_url": "https://codeforces.com/contest/454/submission/97293044",
    "tags": [
      "implementation",
      "*1200"
    ],
    "timestamp": "Nov/01/2020 12:30"
  },
  "CF97293820": {
    "contest_id": 1249,
    "language": "GNU C++17 (64)",
    "path": "codeforces/1249/C1.cpp",
    "problem_index": "C1",
    "problem_name": "Good Numbers (easy version)",
    "problem_url": "https://codeforces.com/contest/1249/problem/C1",
    "submission_id": "CF97293820",
    "submission_url": "https://codeforces.com/contest/1249/submission/97293820",
    "tags": [
      "brute force",
      "greedy",
      "implementation",
      "*1300"
    ],
    "timestamp": "Nov/01/2020 12:42"
  },
  "CF97294935": {
    "contest_id": 1157,
    "language": "GNU C++17 (64)",
    "path": "codeforces/1157/B.cpp",
    "problem_index": "B",
    "problem_name": "Long Number",
    "problem_url": "https://codeforces.com/contest/1157/problem/B",
    "submission_id": "CF97294935",
    "submission_url": "https://codeforces.com/contest/1157/submission/97294935",
    "tags": [
      "greedy",
      "*1300"
    ],
    "timestamp": "Nov/01/2020 12:58"
  },
  "CF97298764": {
    "contest_id": 1366,
    "language": "GNU C++17 (64)",
    "path": "codeforces/1366/C.cpp",
    "problem_index": "C",
    "problem_name": "Palindromic Paths",
    "problem_url": "https://codeforces.com/contest/1366/problem/C",
    "submission_id": "CF97298764",
    "submission_url": "https://codeforces.com/contest/1366/submission/97298764",
    "tags": [
      "greedy",
      "math",
      "*1500"
    ],
    "timestamp": "Nov/01/2020 13:57"
  },
  "CF97306537": {
    "contest_id": 1445,
    "language": "GNU C++17 (64)",
    "path": "codeforces/1445/A.cpp",
    "problem_index": "A",
    "problem_name": "Array Rearrangment",
    "problem_url": "https://codeforces.com/contest/1445/problem/A",
    "submission_id": "CF97306537",
    "submission_url": "https://codeforces.com/contest/1445/submission/97306537",
    "tags": [
      "greedy",
      "sortings",
      "*800"
    ],
    "timestamp": "Nov/01/2020 15:10"
  },
  "CF97325391": {
    "contest_id": 1445,
    "language": "GNU C++17 (64)",
    "path": "codeforces/1445/B.cpp",
    "problem_index": "B",
    "problem_name": "Elimination",
    "problem_url": "https://codeforces.com/contest/1445/problem/B",
    "submission_id": "CF97325391",
    "submission_url": "https://codeforces.com/contest/1445/submission/97325391",
    "tags": [
      "greedy",
      "math",
      "*900"
    ],
    "timestamp": "Nov/01/2020 15:44"
  },
  "CF97364953": {
    "contest_id": 1322,
    "language": "GNU C++17 (64)",
    "path": "codeforces/1322/A.cpp",
    "problem_index": "A",
    "problem_name": "Unusual Competitions",
    "problem_url": "https://codeforces.com/contest/1322/problem/A",
    "submission_id": "CF97364953",
    "submission_url": "https://codeforces.com/contest/1322/submission/97364953",
    "tags": [
      "greedy",
      "*1300"
    ],
    "timestamp": "Nov/01/2020 18:55"
  },
  "CF97371690": {
    "contest_id": 1228,
    "language": "GNU C++17 (64)",
    "path": "codeforces/1228/B.cpp",
    "problem_index": "B",
    "problem_name": "Filling the Grid",
    "problem_url": "https://codeforces.com/contest/1228/problem/B",
    "submission_id": "CF97371690",
    "submission_url": "https://codeforces.com/contest/1228/submission/97371690",
    "tags": [
      "implementation",
      "math",
      "*1400"
    ],
    "timestamp": "Nov/01/2020 20:20"
  },
  "CF98211846": {
    "contest_id": 1431,
    "language": "Kotlin",
    "path": "codeforces/1431/A.kt",
    "problem_index": "A",
    "problem_name": "Selling Hamburgers",
    "problem_url": "https://codeforces.com/contest/1431/problem/A",
    "submission_id": "CF98211846",
    "submission_url": "https://codeforces.com/contest/1431/submission/98211846",
    "tags": [
      "*special problem",
      "*800"
    ],
    "timestamp": "Nov/12/2020 19:06"
  }
}